msfabricutils/__init__.py
msfabricutils/cli/__init__.py
msfabricutils/cli/cli.py
msfabricutils/cli/commands/__init__.py
msfabricutils/cli/commands/capacity.py
msfabricutils/cli/commands/dashboard.py
msfabricutils/cli/commands/data_pipeline.py
msfabricutils/cli/commands/datamart.py
msfabricutils/cli/commands/environment.py
msfabricutils/cli/commands/eventhouse.py
msfabricutils/cli/commands/eventstream.py
msfabricutils/cli/commands/kql_dashboard.py
msfabricutils/cli/commands/kql_database.py
msfabricutils/cli/commands/kql_queryset.py
msfabricutils/cli/commands/lakehouse.py
msfabricutils/cli/commands/long_running_operation.py
msfabricutils/cli/commands/mirrored_database.py
msfabricutils/cli/commands/mirrored_warehouse.py
msfabricutils/cli/commands/ml_experiment.py
msfabricutils/cli/commands/ml_model.py
msfabricutils/cli/commands/notebook.py
msfabricutils/cli/commands/paginated_report.py
msfabricutils/cli/commands/reflex.py
msfabricutils/cli/commands/report.py
msfabricutils/cli/commands/semantic_model.py
msfabricutils/cli/commands/spark_job_definition.py
msfabricutils/cli/commands/sql_endpoint.py
msfabricutils/cli/commands/warehouse.py
msfabricutils/cli/commands/workspace.py
msfabricutils/common/__init__.py
msfabricutils/common/fabric_duckdb_connection.py
msfabricutils/common/quote_identifier.py
msfabricutils/common/remove_none.py
msfabricutils/common/separator_indices.py
msfabricutils/common/shorten_dict_values.py
msfabricutils/common/string_normalization.py
msfabricutils/core/__init__.py
msfabricutils/core/auth.py
msfabricutils/core/fabric_request.py
msfabricutils/core/lakehouse.py
msfabricutils/core/notebook.py
msfabricutils/core/operations.py
msfabricutils/core/sql_endpoint.py
msfabricutils/core/workspace.py
msfabricutils/etl/__init__.py
msfabricutils/etl/config.py
msfabricutils/etl/types.py
msfabricutils/etl/helpers/__init__.py
msfabricutils/etl/helpers/get_max_column_value.py
msfabricutils/etl/helpers/get_min_column_value.py
msfabricutils-0.7.2.dist-info/licenses/LICENSE
msfabricutils-0.7.2.dist-info/METADATA
msfabricutils-0.7.2.dist-info/WHEEL
msfabricutils-0.7.2.dist-info/entry_points.txt
msfabricutils-0.7.2.dist-info/top_level.txt
msfabricutils-0.7.2.dist-info/RECORD
