Metadata-Version: 2.4
Name: msfabricutils
Version: 0.7.2
Summary: A Python library exposes additional functionality to work with Python Notebooks in Microsoft Fabric.
Author: Jimmy Jensen
License: The MIT License (MIT)
Project-URL: Repository, https://github.com/mrjsj/msfabricutils
Keywords: fabric,Microsoft,duckdb,deltalake
Classifier: Programming Language :: Python :: 3
Classifier: Programming Language :: Python :: 3.10
Classifier: Programming Language :: Python :: 3.11
Classifier: Programming Language :: Python :: 3.12
Classifier: License :: OSI Approved :: MIT License
Classifier: Operating System :: OS Independent
Requires-Python: >=3.10
License-File: LICENSE
Requires-Dist: azure-identity>=1.17.1
Requires-Dist: duckdb>=1.2.0
Requires-Dist: deltalake>=0.19.0
Requires-Dist: sqlglot>=25.18
Requires-Dist: polars>=1.7.0
Requires-Dist: typer>=0.15.1
Requires-Dist: pyarrow>=17.0.0
Provides-Extra: docs
Requires-Dist: mkdocs==1.6.1; extra == "docs"
Requires-Dist: mkdocs-material==9.5.47; extra == "docs"
Requires-Dist: mkdocs-gen-files==0.5.0; extra == "docs"
Requires-Dist: mkdocstrings-python; extra == "docs"
Requires-Dist: mkdocs-include-dir-to-nav==1.2.0; extra == "docs"
Provides-Extra: dev
Requires-Dist: pytest>=6.2.5; extra == "dev"
Requires-Dist: ruff>=0.8.1; extra == "dev"
Requires-Dist: freezegun>=1.5.1; extra == "dev"
Requires-Dist: python-dotenv>=1.0.0; extra == "dev"
Dynamic: license-file
